minos/plugins/minos_discovery/__init__.py
minos/plugins/minos_discovery/client.py
minos_discovery_minos-0.7.0.dist-info/LICENSE
minos_discovery_minos-0.7.0.dist-info/WHEEL
minos_discovery_minos-0.7.0.dist-info/METADATA
minos_discovery_minos-0.7.0.dist-info/RECORD
